{
  "name": "@ryanatkn/earbetter",
  "version": "0.2.0",
  "modules": {
    "./ac.js": {
      "path": "ac.ts",
      "declarations": [
        {
          "name": "get_ac",
          "kind": "function"
        },
        {
          "name": "set_ac",
          "kind": "function"
        },
        {
          "name": "create_ac",
          "kind": "function"
        }
      ]
    },
    "./colors.js": {
      "path": "colors.ts",
      "declarations": [
        {
          "name": "Hsl",
          "kind": "type"
        },
        {
          "name": "Hue",
          "kind": "type"
        },
        {
          "name": "Saturation",
          "kind": "type"
        },
        {
          "name": "Lightness",
          "kind": "type"
        },
        {
          "name": "Rgb",
          "kind": "type"
        },
        {
          "name": "Red",
          "kind": "type"
        },
        {
          "name": "Green",
          "kind": "type"
        },
        {
          "name": "Blue",
          "kind": "type"
        },
        {
          "name": "hue_to_rgb",
          "kind": "function"
        },
        {
          "name": "rgb_to_hex",
          "kind": "function"
        },
        {
          "name": "hex_to_rgb",
          "kind": "function"
        },
        {
          "name": "hex_string_to_rgb",
          "kind": "function"
        },
        {
          "name": "rgb_to_hex_string",
          "kind": "function"
        },
        {
          "name": "to_hex",
          "kind": "function"
        },
        {
          "name": "rgb_to_hsl",
          "kind": "function"
        },
        {
          "name": "hsl_to_rgb",
          "kind": "function"
        },
        {
          "name": "hsl_to_hex",
          "kind": "function"
        },
        {
          "name": "hsl_to_hex_string",
          "kind": "function"
        },
        {
          "name": "hsl_to_string",
          "kind": "function"
        },
        {
          "name": "hex_string_to_hsl",
          "kind": "function"
        }
      ]
    },
    "./dom.js": {
      "path": "dom.ts",
      "declarations": [
        {
          "name": "find_previous_sibling",
          "kind": "function"
        },
        {
          "name": "find_next_sibling",
          "kind": "function"
        }
      ]
    },
    "./earbetter/app.js": {
      "path": "earbetter/app.ts",
      "declarations": [
        {
          "name": "AppData",
          "kind": "variable"
        },
        {
          "name": "get_app",
          "kind": "function"
        },
        {
          "name": "set_app",
          "kind": "function"
        },
        {
          "name": "App",
          "kind": "class"
        }
      ]
    },
    "./earbetter/ControlsInstructions.svelte": {
      "path": "earbetter/ControlsInstructions.svelte",
      "declarations": []
    },
    "./earbetter/Earbetter.svelte": {
      "path": "earbetter/Earbetter.svelte",
      "declarations": []
    },
    "./earbetter/Level.svelte": {
      "path": "earbetter/Level.svelte",
      "declarations": []
    },
    "./earbetter/level.js": {
      "path": "earbetter/level.ts",
      "declarations": [
        {
          "name": "DEFAULT_NOTE_DURATION",
          "kind": "variable"
        },
        {
          "name": "DEFAULT_NOTE_DURATION_2",
          "kind": "variable"
        },
        {
          "name": "DEFAULT_NOTE_DURATION_FAILED",
          "kind": "variable"
        },
        {
          "name": "DEFAULT_FEEDBACK_DURATION",
          "kind": "variable"
        },
        {
          "name": "DEFAULT_SEQUENCE_LENGTH",
          "kind": "variable"
        },
        {
          "name": "DEFAULT_TRIAL_COUNT",
          "kind": "variable"
        },
        {
          "name": "DEFAULT_LEVEL_NAME",
          "kind": "variable"
        },
        {
          "name": "DEFAULT_INTERVALS",
          "kind": "variable"
        },
        {
          "name": "DEFAULT_TONICS",
          "kind": "variable"
        },
        {
          "name": "DEFAULT_MIN_NOTE",
          "kind": "variable"
        },
        {
          "name": "DEFAULT_MAX_NOTE",
          "kind": "variable"
        },
        {
          "name": "LevelId",
          "kind": "variable"
        },
        {
          "name": "create_level_id",
          "kind": "function"
        },
        {
          "name": "LevelName",
          "kind": "variable"
        },
        {
          "name": "LevelData",
          "kind": "variable"
        },
        {
          "name": "LevelHashData",
          "kind": "variable"
        },
        {
          "name": "Status",
          "kind": "type"
        },
        {
          "name": "Level",
          "kind": "type"
        },
        {
          "name": "Trial",
          "kind": "type"
        },
        {
          "name": "create_level",
          "kind": "function"
        },
        {
          "name": "to_play_level_url",
          "kind": "function"
        },
        {
          "name": "MistakesLevelStats",
          "kind": "variable"
        },
        {
          "name": "LevelStats",
          "kind": "variable"
        },
        {
          "name": "DEFAULT_LEVEL_STATS",
          "kind": "variable"
        },
        {
          "name": "add_mistakes_to_level_stats",
          "kind": "function"
        },
        {
          "name": "MISTAKE_HISTORY_LENGTH",
          "kind": "variable"
        }
      ]
    },
    "./earbetter/LevelForm.svelte": {
      "path": "earbetter/LevelForm.svelte",
      "declarations": []
    },
    "./earbetter/LevelMap.svelte": {
      "path": "earbetter/LevelMap.svelte",
      "declarations": []
    },
    "./earbetter/LevelMapItem.svelte": {
      "path": "earbetter/LevelMapItem.svelte",
      "declarations": []
    },
    "./earbetter/LevelMapItems.svelte": {
      "path": "earbetter/LevelMapItems.svelte",
      "declarations": []
    },
    "./earbetter/LevelProgressIndicator.svelte": {
      "path": "earbetter/LevelProgressIndicator.svelte",
      "declarations": []
    },
    "./earbetter/LevelStatsSummary.svelte": {
      "path": "earbetter/LevelStatsSummary.svelte",
      "declarations": []
    },
    "./earbetter/project.js": {
      "path": "earbetter/project.ts",
      "declarations": [
        {
          "name": "ProjectId",
          "kind": "variable"
        },
        {
          "name": "create_project_id",
          "kind": "function"
        },
        {
          "name": "ProjectName",
          "kind": "variable"
        },
        {
          "name": "ProjectMetadata",
          "kind": "variable"
        },
        {
          "name": "ProjectData",
          "kind": "variable"
        }
      ]
    },
    "./earbetter/ProjectEditor.svelte": {
      "path": "earbetter/ProjectEditor.svelte",
      "declarations": []
    },
    "./earbetter/ProjectForm.svelte": {
      "path": "earbetter/ProjectForm.svelte",
      "declarations": []
    },
    "./earbetter/ProjectItem.svelte": {
      "path": "earbetter/ProjectItem.svelte",
      "declarations": []
    },
    "./earbetter/ProjectItems.svelte": {
      "path": "earbetter/ProjectItems.svelte",
      "declarations": []
    },
    "./earbetter/Projects.svelte": {
      "path": "earbetter/Projects.svelte",
      "declarations": []
    },
    "./earbetter/realm_helpers.js": {
      "path": "earbetter/realm_helpers.ts",
      "declarations": [
        {
          "name": "to_default_scale_realm",
          "kind": "function"
        }
      ]
    },
    "./earbetter/realm.js": {
      "path": "earbetter/realm.ts",
      "declarations": [
        {
          "name": "RealmId",
          "kind": "variable"
        },
        {
          "name": "create_realm_id",
          "kind": "function"
        },
        {
          "name": "RealmName",
          "kind": "variable"
        },
        {
          "name": "RealmData",
          "kind": "variable"
        }
      ]
    },
    "./earbetter/RealmEditor.svelte": {
      "path": "earbetter/RealmEditor.svelte",
      "declarations": []
    },
    "./earbetter/RealmForm.svelte": {
      "path": "earbetter/RealmForm.svelte",
      "declarations": []
    },
    "./earbetter/RealmItem.svelte": {
      "path": "earbetter/RealmItem.svelte",
      "declarations": []
    },
    "./earbetter/RealmItems.svelte": {
      "path": "earbetter/RealmItems.svelte",
      "declarations": []
    },
    "./earbetter/Realms.svelte": {
      "path": "earbetter/Realms.svelte",
      "declarations": []
    },
    "./earbetter/RealmStatsSummary.svelte": {
      "path": "earbetter/RealmStatsSummary.svelte",
      "declarations": []
    },
    "./earbetter/TrialProgressIndicator.svelte": {
      "path": "earbetter/TrialProgressIndicator.svelte",
      "declarations": []
    },
    "./emoji.js": {
      "path": "emoji.ts",
      "declarations": [
        {
          "name": "Emoji",
          "kind": "variable"
        },
        {
          "name": "emojis",
          "kind": "variable"
        }
      ]
    },
    "./entity.js": {
      "path": "entity.ts",
      "declarations": [
        {
          "name": "to_next_name",
          "kind": "function"
        }
      ]
    },
    "./helpers.js": {
      "path": "helpers.ts",
      "declarations": [
        {
          "name": "Frequency",
          "kind": "type"
        },
        {
          "name": "Milliseconds",
          "kind": "type"
        },
        {
          "name": "Volume",
          "kind": "variable"
        },
        {
          "name": "DEFAULT_VOLUME",
          "kind": "variable"
        },
        {
          "name": "DEFAULT_VOLUME_INCREMENT",
          "kind": "variable"
        },
        {
          "name": "DEFAULT_VELOCITY",
          "kind": "variable"
        },
        {
          "name": "with_velocity",
          "kind": "function"
        },
        {
          "name": "get_volume",
          "kind": "function"
        },
        {
          "name": "set_volume",
          "kind": "function"
        },
        {
          "name": "adjust_volume",
          "kind": "function"
        },
        {
          "name": "VOLUME_TO_GAIN_EXPONENT",
          "kind": "variable"
        },
        {
          "name": "volume_to_gain",
          "kind": "function"
        },
        {
          "name": "SMOOTH_GAIN_TIME_CONSTANT",
          "kind": "variable"
        },
        {
          "name": "Instrument",
          "kind": "variable"
        },
        {
          "name": "instruments",
          "kind": "variable"
        },
        {
          "name": "DEFAULT_INSTRUMENT",
          "kind": "variable"
        },
        {
          "name": "get_instrument",
          "kind": "function"
        },
        {
          "name": "set_instrument",
          "kind": "function"
        }
      ]
    },
    "./id.js": {
      "path": "id.ts",
      "declarations": [
        {
          "name": "to_random_id",
          "kind": "function"
        }
      ]
    },
    "./InitMidiButton.svelte": {
      "path": "InitMidiButton.svelte",
      "declarations": []
    },
    "./InstrumentControl.svelte": {
      "path": "InstrumentControl.svelte",
      "declarations": []
    },
    "./IntervalsInput.svelte": {
      "path": "IntervalsInput.svelte",
      "declarations": []
    },
    "./midi_access.js": {
      "path": "midi_access.ts",
      "declarations": [
        {
          "name": "midi_access",
          "kind": "variable"
        },
        {
          "name": "request_access",
          "kind": "function"
        }
      ]
    },
    "./midi_helpers.js": {
      "path": "midi_helpers.ts",
      "declarations": [
        {
          "name": "MidiMessage",
          "kind": "type"
        },
        {
          "name": "parse_midi_message",
          "kind": "function"
        },
        {
          "name": "request_midi_access",
          "kind": "function"
        }
      ]
    },
    "./MidiInput.svelte": {
      "path": "MidiInput.svelte",
      "declarations": []
    },
    "./MidiRangeControl.svelte": {
      "path": "MidiRangeControl.svelte",
      "declarations": []
    },
    "./music.js": {
      "path": "music.ts",
      "declarations": [
        {
          "name": "DEFAULT_TUNING",
          "kind": "variable"
        },
        {
          "name": "NOTE_FLAT_SYMBOL",
          "kind": "variable"
        },
        {
          "name": "NOTE_SHARP_SYMBOL",
          "kind": "variable"
        },
        {
          "name": "NoteName",
          "kind": "type"
        },
        {
          "name": "chromas",
          "kind": "variable"
        },
        {
          "name": "Chroma",
          "kind": "type"
        },
        {
          "name": "Octave",
          "kind": "type"
        },
        {
          "name": "Semitones",
          "kind": "variable"
        },
        {
          "name": "Intervals",
          "kind": "variable"
        },
        {
          "name": "serialize_intervals",
          "kind": "function"
        },
        {
          "name": "parse_intervals",
          "kind": "function"
        },
        {
          "name": "compute_naturals",
          "kind": "function"
        },
        {
          "name": "transpose",
          "kind": "function"
        },
        {
          "name": "chroma_to_hue",
          "kind": "variable"
        },
        {
          "name": "chroma_to_hsl",
          "kind": "variable"
        },
        {
          "name": "chroma_to_hsl_string",
          "kind": "variable"
        },
        {
          "name": "interval_short_names",
          "kind": "variable"
        },
        {
          "name": "IntervalShortNames",
          "kind": "type"
        },
        {
          "name": "interval_names",
          "kind": "variable"
        },
        {
          "name": "IntervalNames",
          "kind": "type"
        },
        {
          "name": "get_enabled_notes",
          "kind": "function"
        },
        {
          "name": "set_enabled_notes",
          "kind": "function"
        },
        {
          "name": "ScaleName",
          "kind": "variable"
        },
        {
          "name": "Scale",
          "kind": "variable"
        },
        {
          "name": "scales",
          "kind": "variable"
        },
        {
          "name": "DEFAULT_SCALE",
          "kind": "variable"
        },
        {
          "name": "scale_by_name",
          "kind": "variable"
        },
        {
          "name": "lookup_scale",
          "kind": "function"
        },
        {
          "name": "to_scale_notes",
          "kind": "function"
        },
        {
          "name": "get_scale",
          "kind": "function"
        },
        {
          "name": "set_scale",
          "kind": "function"
        },
        {
          "name": "PitchClass",
          "kind": "variable"
        },
        {
          "name": "pitch_classes",
          "kind": "variable"
        },
        {
          "name": "DEFAULT_PITCH_CLASS",
          "kind": "variable"
        },
        {
          "name": "pitch_class_aliases",
          "kind": "variable"
        },
        {
          "name": "get_key",
          "kind": "function"
        },
        {
          "name": "set_key",
          "kind": "function"
        },
        {
          "name": "to_notes_in_scale",
          "kind": "function"
        },
        {
          "name": "Midi",
          "kind": "variable"
        },
        {
          "name": "MIDI_MIN",
          "kind": "variable"
        },
        {
          "name": "MIDI_MAX",
          "kind": "variable"
        },
        {
          "name": "midis",
          "kind": "variable"
        },
        {
          "name": "is_midi",
          "kind": "function"
        },
        {
          "name": "midi_to_freq",
          "kind": "function"
        },
        {
          "name": "freq_to_midi",
          "kind": "function"
        },
        {
          "name": "freq_to_midi_safe",
          "kind": "function"
        },
        {
          "name": "midi_chromas",
          "kind": "variable"
        },
        {
          "name": "midi_pitch_classes",
          "kind": "variable"
        },
        {
          "name": "midi_octaves",
          "kind": "variable"
        },
        {
          "name": "midi_names",
          "kind": "variable"
        },
        {
          "name": "midi_naturals",
          "kind": "variable"
        },
        {
          "name": "Notes",
          "kind": "variable"
        },
        {
          "name": "serialize_notes",
          "kind": "function"
        },
        {
          "name": "parse_notes",
          "kind": "function"
        }
      ]
    },
    "./NotesInput.svelte": {
      "path": "NotesInput.svelte",
      "declarations": []
    },
    "./Piano.svelte": {
      "path": "Piano.svelte",
      "declarations": []
    },
    "./piano.js": {
      "path": "piano.ts",
      "declarations": [
        {
          "name": "Piano",
          "kind": "type"
        },
        {
          "name": "PianoKey",
          "kind": "type"
        },
        {
          "name": "compute_piano",
          "kind": "function"
        }
      ]
    },
    "./PianoKey.svelte": {
      "path": "PianoKey.svelte",
      "declarations": []
    },
    "./play_note.js": {
      "path": "play_note.ts",
      "declarations": [
        {
          "name": "play_note",
          "kind": "function"
        },
        {
          "name": "StopPlaying",
          "kind": "type"
        },
        {
          "name": "playing_notes",
          "kind": "variable"
        },
        {
          "name": "start_playing_note",
          "kind": "function"
        },
        {
          "name": "start_playing",
          "kind": "function"
        },
        {
          "name": "stop_playing",
          "kind": "function"
        }
      ]
    },
    "./projects/default_project.js": {
      "path": "projects/default_project.ts",
      "declarations": [
        {
          "name": "default",
          "kind": "function"
        }
      ]
    },
    "./SelectNotesControl.svelte": {
      "path": "SelectNotesControl.svelte",
      "declarations": []
    },
    "./storage.js": {
      "path": "storage.ts",
      "declarations": [
        {
          "name": "load_from_storage",
          "kind": "function"
        },
        {
          "name": "set_in_storage",
          "kind": "function"
        }
      ]
    },
    "./style.css": {
      "path": "style.css",
      "declarations": []
    },
    "./TextBurst.svelte": {
      "path": "TextBurst.svelte",
      "declarations": []
    },
    "./url.js": {
      "path": "url.ts",
      "declarations": [
        {
          "name": "parse_from_hash",
          "kind": "function"
        },
        {
          "name": "serialize_to_hash",
          "kind": "function"
        }
      ]
    },
    "./VolumeControl.svelte": {
      "path": "VolumeControl.svelte",
      "declarations": []
    },
    "./WebMIDI.js": {
      "path": "WebMIDI.ts",
      "declarations": [
        {
          "name": "requestMIDIAccess",
          "kind": "type"
        },
        {
          "name": "MIDIOptions",
          "kind": "type"
        },
        {
          "name": "MIDIAccess",
          "kind": "type"
        },
        {
          "name": "MIDIInputMap",
          "kind": "type"
        },
        {
          "name": "MIDIInput",
          "kind": "type"
        },
        {
          "name": "MIDIOutputMap",
          "kind": "type"
        },
        {
          "name": "MIDIOutput",
          "kind": "type"
        },
        {
          "name": "MIDIPort",
          "kind": "type"
        },
        {
          "name": "MIDIPortID",
          "kind": "type"
        },
        {
          "name": "MIDIPortType",
          "kind": "type"
        },
        {
          "name": "MIDIPortDeviceState",
          "kind": "type"
        },
        {
          "name": "MIDIPortConnectionState",
          "kind": "type"
        },
        {
          "name": "MIDIMessageEvent",
          "kind": "type"
        },
        {
          "name": "MIDIMessageEventInit",
          "kind": "type"
        },
        {
          "name": "MIDIMessageData",
          "kind": "type"
        },
        {
          "name": "MIDIConnectionEvent",
          "kind": "type"
        },
        {
          "name": "MIDIConnectionEventInit",
          "kind": "type"
        },
        {
          "name": "MIDICommand",
          "kind": null
        },
        {
          "name": "MIDIChannel",
          "kind": "type"
        }
      ]
    }
  }
}
